Workbook

Sheet Dashboard
A1: OEE & TPM Loss Reduction — Executive Dashboard
A2: High-Speed Packaging Line | 12-Week Study | Baseline -> Improved
A4: BASELINE OEE (Wks 1-4) | D4: IMPROVED OEE (Wks 9-12) | G4: WORLD-CLASS TARGET | J4: ANNUALIZED SAVINGS | M4: CHANGEOVER TIME CUT
A5: =OEE_Calc!E109 -> 0.69463276 | D5: =OEE_Calc!E111 -> 0.83456056 | G5: =Assumptions!$B$7 -> 0.85 | J5: =Results_Summary!B18 -> 1917150.6 | M5: =AVERAGEIF(Raw_Data!C5:C88,"Baseline",Raw_Data!F5:F88)-AVERAGEIF(Raw_Data!C5:C88,"Improved",Raw_Data!F5:F88) -> 28.45
D7: ="+"&TEXT(OEE_Calc!E111-OEE_Calc!E109,"0.0%")&" pts" -> +14.0% pts

Sheet Cover
A1: OEE Improvement & TPM-Driven Loss Reduction
A2: High-Speed Packaging Line | Manufacturing Excellence / Supply Chain Project
A4: Project Objective
A5: Improve Overall Equipment Effectiveness (OEE) on a high-speed primary packaging line by
A6: systematically eliminating the Six Big Losses using a Total Productive Maintenance (TPM)
A7: framework, translating equipment reliability gains into supply chain throughput, cost, and
A8: service-level improvement.
A10: Scope
A11: One high-speed packaging line, ideal run rate 100 packs/minute, running 3 shifts x 24/7.
A12: 12-week study: Weeks 1-4 Baseline diagnostics, Weeks 5-8 TPM Implementation, Weeks 9-12 Improved/Sustain.
A14: Methodology
A15: 1. Baseline: capture daily downtime, output and reject data; calculate Availability, Performance, Quality, OEE.
... A30: Note: all production figures are illustrative/simulated for interview preparation, built to reflect realistic FMCG high-speed line performance.

Sheet Assumptions
A1: Assumptions & Targets
A2: Key inputs referenced by every calculation sheet (edit the blue cells)
A4: Assumption | B4: Value | C4: Unit | D4: Notes
A5: Ideal Run Rate | B5: 100 | C5: packs/min | D5: Design/nameplate speed of the high-speed line
A6: Planned Production Time | B6: 1380 | C6: min/day | D6: 24-hr operation less scheduled breaks/meetings (60 min)
A7: World-Class OEE Target | B7: 0.85 | C7: % | D7: Common industry benchmark (Nakajima)
A8: Cost per Minute of Downtime | B8: 50 | C8: $/min | D8: Lost production value: line rate x contribution margin/unit
A9: Cost per Rejected Unit | B9: 0.15 | C9: $/unit | D9: Material + packaging + rework cost per rejected pack
A10: Operating Days per Year | B10: 350 | C10: days/yr | D10: Continuous operation, excl. planned shutdowns

Sheet Raw_Data
A1: Raw Production Data
A2: Daily line data — blue cells are inputs; grey cells are formulas
A4: Date | B4: Week | C4: Phase | D4: Planned Time (min) | E4: Breakdown (min) | F4: Changeover/Setup (min) | G4: Minor Stops (min) | H4: Total Downtime (min) | I4: Operating Time (min) | J4: Total Pieces | K4: Reject Pieces | L4: Good Pieces
A5: 2025-01-06 | B5: 1 | C5: Baseline | D5: =Assumptions!$B$6 -> 1380 | E5: 121 | F5: 73.9 | G5: 59.5 | H5: =SUM(E5:G5) -> 254.4 | I5: =D5-H5 -> 1125.6 | J5: 100231 | K5: 4894 | L5: =J5-K5 -> 95337
A6: 2025-01-07 | B6: 1 | C6: Baseline | D6: =Assumptions!$B$6 -> 1380 | E6: 112.2 | F6: 87.6 | G6: 60.4 | H6: =SUM(E6:G6) -> 260.2 | I6: =D6-H6 -> 1119.8 | J6: 95252 | K6: 5021 | L6: =J6-K6 -> 90231
A7: 2025-01-08 | B7: 1 | C7: Baseline | D7: =Assumptions!$B$6 -> 1380 | E7: 109.4 | F7: 71.3 | G7: 56.7 | H7: =SUM(E7:G7) -> 237.4 | I7: =D7-H7 -> 1142.6 | J7: 93891 | K7: 3885 | L7: =J7-K7 -> 90006
A8: 2025-01-09 | B8: 1 | C8: Baseline | D8: =Assumptions!$B$6 -> 1380 | E8: 108.3 | F8: 66.9 | G8: 57.2 | H8: =SUM(E8:G8) -> 232.4 | I8: =D8-H8 -> 1147.6 | J8: 96614 | K8: 4148 | L8: =J8-K8 -> 92466
A9: 2025-01-10 | B9: 1 | C9: Baseline | D9: =Assumptions!$B$6 -> 1380 | E9: 132.6 | F9: 73.2 | G9: 55.5 | H9: =SUM(E9:G9) -> 261.3 | I9: =D9-H9 -> 1118.7 | J9: 93024 | K9: 4398 | L9: =J9-K9 -> 88626
A10: 2025-01-11 | B10: 1 | C10: Baseline | D10: =Assumptions!$B$6 -> 1380 | E10: 116.3 | F10: 65.8 | G10: 57.6 | H10: =SUM(E10:G10) -> 239.7 | I10: =D10-H10 -> 1140.3 | J10: 96691 | K10: 4694 | L10: =J10-K10 -> 91997
A11: 2025-01-12 | B11: 1 | C11: Baseline | D11: =Assumptions!$B$6 -> 1380 | E11: 107.8 | F11: 89.8 | G11: 54.9 | H11: =SUM(E11:G11) -> 252.5 | I11: =D11-H11 -> 1127.5 | J11: 94580 | K11: 5118 | L11: =J11-K11 -> 89462
A12: 2025-01-13 | B12: 2 | C12: Baseline | D12: =Assumptions!$B$6 -> 1380 | E12: 94 | F12: 73 | G12: 38.6 | H12: =SUM(E12:G12) -> 205.6 | I12: =D12-H12 -> 1174.4 | J12: 98735 | K12: 4765 | L12: =J12-K12 -> 93970
A13: 2025-01-14 | B13: 2 | C13: Baseline | D13: =Assumptions!$B$6 -> 1380 | E13: 117.5 | F13: 72.7 | G13: 51.5 | H13: =SUM(E13:G13) -> 241.7 | I13: =D13-H13 -> 1138.3 | J13: 98037 | K13: 3910 | L13: =J13-K13 -> 94127
A14: 2025-01-15 | B14: 2 | C14: Baseline | D14: =Assumptions!$B$6 -> 1380 | E14: 100 | F14: 67.7 | G14: 59.7 | H14: =SUM(E14:G14) -> 227.4 | I14: =D14-H14 -> 1152.6 | J14: 100758 | K14: 3875 | L14: =J14-K14 -> 96883
A15: 2025-01-16 | B15: 2 | C15: Baseline | D15: =Assumptions!$B$6 -> 1380 | E15: 112.5 | F15: 68.3 | G15: 47.5 | H15: =SUM(E15:G15) -> 228.3 | I15: =D15-H15 -> 1151.7 | J15: 101289 | K15: 5310 | L15: =J15-K15 -> 95979
A16: 2025-01-17 | B16: 2 | C16: Baseline | D16: =Assumptions!$B$6 -> 1380 | E16: 119.8 | F16: 64.6 | G16: 50.1 | H16: =SUM(E16:G16) -> 234.5 | I16: =D16-H16 -> 1145.5 | J16: 100099 | K16: 5220 | L16: =J16-K16 -> 94879
... A88: 2025-03-30 | B88: 12 | C88: Improved | D88: =Assumptions!$B$6 -> 1380 | E88: 36 | F88: 47.4 | G88: 25.8 | H88: =SUM(E88:G88) -> 109.2 | I88: =D88-H88 -> 1270.8 | J88: 122449 | K88: 2490 | L88: =J88-K88 -> 119959

Sheet OEE_Calc
A1: OEE Calculation Engine
A2: Availability x Performance x Quality — fully formula-driven from Raw_Data
A4: Date | B4: Week | C4: Phase | D4: Availability | E4: Performance | F4: Quality | G4: OEE | H4: Speed Loss (min) | I4: Quality Loss (min)
A5: =Raw_Data!A5 -> 2025-01-06 | B5: =Raw_Data!B5 -> 1 | C5: =Raw_Data!C5 -> Baseline | D5: =IFERROR(Raw_Data!I5/Raw_Data!D5,0) -> 0.81565217 | E5: =IFERROR(Raw_Data!J5/(Raw_Data!I5*Assumptions!$B$5),0) -> 0.89046731 | F5: =IFERROR(Raw_Data!L5/Raw_Data!J5,0) -> 0.95117279 | G5: =D5*E5*F5 -> 0.69084783 | H5: =MAX(0,(Raw_Data!I5*Assumptions!$B$5-Raw_Data!J5)/Assumptions!$B$5) -> 123.29 | I5: =IFERROR(Raw_Data!K5/Assumptions!$B$5,0) -> 48.94
A6: =Raw_Data!A6 -> 2025-01-07 | B6: =Raw_Data!B6 -> 1 | C6: =Raw_Data!C6 -> Baseline | D6: =IFERROR(Raw_Data!I6/Raw_Data!D6,0) -> 0.81144928 | E6: =IFERROR(Raw_Data!J6/(Raw_Data!I6*Assumptions!$B$5),0) -> 0.85061618 | F6: =IFERROR(Raw_Data!L6/Raw_Data!J6,0) -> 0.9472872 | G6: =D6*E6*F6 -> 0.65384783 | H6: =MAX(0,(Raw_Data!I6*Assumptions!$B$5-Raw_Data!J6)/Assumptions!$B$5) -> 167.28 | I6: =IFERROR(Raw_Data!K6/Assumptions!$B$5,0) -> 50.21
A7: =Raw_Data!A7 -> 2025-01-08 | B7: =Raw_Data!B7 -> 1 | C7: =Raw_Data!C7 -> Baseline | D7: =IFERROR(Raw_Data!I7/Raw_Data!D7,0) -> 0.82797101 | E7: =IFERROR(Raw_Data!J7/(Raw_Data!I7*Assumptions!$B$5),0) -> 0.82173114 | F7: =IFERROR(Raw_Data!L7/Raw_Data!J7,0) -> 0.95862223 | G7: =D7*E7*F7 -> 0.65221739 | H7: =MAX(0,(Raw_Data!I7*Assumptions!$B$5-Raw_Data!J7)/Assumptions!$B$5) -> 203.69 | I7: =IFERROR(Raw_Data!K7/Assumptions!$B$5,0) -> 38.85
A8: =Raw_Data!A8 -> 2025-01-09 | B8: =Raw_Data!B8 -> 1 | C8: =Raw_Data!C8 -> Baseline | D8: =IFERROR(Raw_Data!I8/Raw_Data!D8,0) -> 0.8315942 | E8: =IFERROR(Raw_Data!J8/(Raw_Data!I8*Assumptions!$B$5),0) -> 0.8418787 | F8: =IFERROR(Raw_Data!L8/Raw_Data!J8,0) -> 0.95706626 | G8: =D8*E8*F8 -> 0.67004348 | H8: =MAX(0,(Raw_Data!I8*Assumptions!$B$5-Raw_Data!J8)/Assumptions!$B$5) -> 181.46 | I8: =IFERROR(Raw_Data!K8/Assumptions!$B$5,0) -> 41.48
A9: =Raw_Data!A9 -> 2025-01-10 | B9: =Raw_Data!B9 -> 1 | C9: =Raw_Data!C9 -> Baseline | D9: =IFERROR(Raw_Data!I9/Raw_Data!D9,0) -> 0.81065217 | E9: =IFERROR(Raw_Data!J9/(Raw_Data!I9*Assumptions!$B$5),0) -> 0.8315366 | F9: =IFERROR(Raw_Data!L9/Raw_Data!J9,0) -> 0.95272188 | G9: =D9*E9*F9 -> 0.64221739 | H9: =MAX(0,(Raw_Data!I9*Assumptions!$B$5-Raw_Data!J9)/Assumptions!$B$5) -> 188.46 | I9: =IFERROR(Raw_Data!K9/Assumptions!$B$5,0) -> 43.98
A10: =Raw_Data!A10 -> 2025-01-11 | B10: =Raw_Data!B10 -> 1 | C10: =Raw_Data!C10 -> Baseline | D10: =IFERROR(Raw_Data!I10/Raw_Data!D10,0) -> 0.82630435 | E10: =IFERROR(Raw_Data!J10/(Raw_Data!I10*Assumptions!$B$5),0) -> 0.84794352 | F10: =IFERROR(Raw_Data!L10/Raw_Data!J10,0) -> 0.9514536 | G10: =D10*E10*F10 -> 0.66664493 | H10: =MAX(0,(Raw_Data!I10*Assumptions!$B$5-Raw_Data!J10)/Assumptions!$B$5) -> 173.39 | I10: =IFERROR(Raw_Data!K10/Assumptions!$B$5,0) -> 46.94
A11: =Raw_Data!A11 -> 2025-01-12 | B11: =Raw_Data!B11 -> 1 | C11: =Raw_Data!C11 -> Baseline | D11: =IFERROR(Raw_Data!I11/Raw_Data!D11,0) -> 0.81702899 | E11: =IFERROR(Raw_Data!J11/(Raw_Data!I11*Assumptions!$B$5),0) -> 0.83884701 | F11: =IFERROR(Raw_Data!L11/Raw_Data!J11,0) -> 0.94588708 | G11: =D11*E11*F11 -> 0.64827536 | H11: =MAX(0,(Raw_Data!I11*Assumptions!$B$5-Raw_Data!J11)/Assumptions!$B$5) -> 181.7 | I11: =IFERROR(Raw_Data!K11/Assumptions!$B$5,0) -> 51.18
A12: =Raw_Data!A12 -> 2025-01-13 | B12: =Raw_Data!B12 -> 2 | C12: =Raw_Data!C12 -> Baseline | D12: =IFERROR(Raw_Data!I12/Raw_Data!D12,0) -> 0.85101449 | E12: =IFERROR(Raw_Data!J12/(Raw_Data!I12*Assumptions!$B$5),0) -> 0.84072718 | F12: =IFERROR(Raw_Data!L12/Raw_Data!J12,0) -> 0.9517395 | G12: =D12*E12*F12 -> 0.68094203 | H12: =MAX(0,(Raw_Data!I12*Assumptions!$B$5-Raw_Data!J12)/Assumptions!$B$5) -> 187.05 | I12: =IFERROR(Raw_Data!K12/Assumptions!$B$5,0) -> 47.65
A13: =Raw_Data!A13 -> 2025-01-14 | B13: =Raw_Data!B13 -> 2 | C13: =Raw_Data!C13 -> Baseline | D13: =IFERROR(Raw_Data!I13/Raw_Data!D13,0) -> 0.82485507 | E13: =IFERROR(Raw_Data!J13/(Raw_Data!I13*Assumptions!$B$5),0) -> 0.86125802 | F13: =IFERROR(Raw_Data!L13/Raw_Data!J13,0) -> 0.9601171 | G13: =D13*E13*F13 -> 0.68207971 | H13: =MAX(0,(Raw_Data!I13*Assumptions!$B$5-Raw_Data!J13)/Assumptions!$B$5) -> 157.93 | I13: =IFERROR(Raw_Data!K13/Assumptions!$B$5,0) -> 39.1
A14: =Raw_Data!A14 -> 2025-01-15 | B14: =Raw_Data!B14 -> 2 | C14: =Raw_Data!C14 -> Baseline | D14: =IFERROR(Raw_Data!I14/Raw_Data!D14,0) -> 0.83521739 | E14: =IFERROR(Raw_Data!J14/(Raw_Data!I14*Assumptions!$B$5),0) -> 0.87418011 | F14: =IFERROR(Raw_Data!L14/Raw_Data!J14,0) -> 0.96154152 | G14: =D14*E14*F14 -> 0.70205072 | H14: =MAX(0,(Raw_Data!I14*Assumptions!$B$5-Raw_Data!J14)/Assumptions!$B$5) -> 145.02 | I14: =IFERROR(Raw_Data!K14/Assumptions!$B$5,0) -> 38.75
A15: =Raw_Data!A15 -> 2025-01-16 | B15: =Raw_Data!B15 -> 2 | C15: =Raw_Data!C15 -> Baseline | D15: =IFERROR(Raw_Data!I15/Raw_Data!D15,0) -> 0.83456522 | E15: =IFERROR(Raw_Data!J15/(Raw_Data!I15*Assumptions!$B$5),0) -> 0.87947382 | F15: =IFERROR(Raw_Data!L15/Raw_Data!J15,0) -> 0.94757575 | G15: =D15*E15*F15 -> 0.6955 | H15: =MAX(0,(Raw_Data!I15*Assumptions!$B$5-Raw_Data!J15)/Assumptions!$B$5) -> 138.81 | I15: =IFERROR(Raw_Data!K15/Assumptions!$B$5,0) -> 53.1
A16: =Raw_Data!A16 -> 2025-01-17 | B16: =Raw_Data!B16 -> 2 | C16: =Raw_Data!C16 -> Baseline | D16: =IFERROR(Raw_Data!I16/Raw_Data!D16,0) -> 0.83007246 | E16: =IFERROR(Raw_Data!J16/(Raw_Data!I16*Assumptions!$B$5),0) -> 0.87384548 | F16: =IFERROR(Raw_Data!L16/Raw_Data!J16,0) -> 0.94785163 | G16: =D16*E16*F16 -> 0.68752899 | H16: =MAX(0,(Raw_Data!I16*Assumptions!$B$5-Raw_Data!J16)/Assumptions!$B$5) -> 144.51 | I16: =IFERROR(Raw_Data!K16/Assumptions!$B$5,0) -> 52.2
... A88: =Raw_Data!A88 -> 2025-03-30 | B88: =Raw_Data!B88 -> 12 | C88: =Raw_Data!C88 -> Improved | D88: =IFERROR(Raw_Data!I88/Raw_Data!D88,0) -> 0.92086957 | E88: =IFERROR(Raw_Data!J88/(Raw_Data!I88*Assumptions!$B$5),0) -> 0.96355839 | F88: =IFERROR(Raw_Data!L88/Raw_Data!J88,0) -> 0.979665 | G88: =D88*E88*F88 -> 0.86926812 | H88: =MAX(0,(Raw_Data!I88*Assumptions!$B$5-Raw_Data!J88)/Assumptions!$B$5) -> 46.31 | I88: =IFERROR(Raw_Data!K88/Assumptions!$B$5,0) -> 24.9
A91: Weekly Roll-Up
A92: Week | B92: Phase | C92: Avg Availability | D92: Avg Performance | E92: Avg Quality | F92: Avg OEE | G92: Target
A93: 1 | B93: Baseline | C93: =AVERAGEIF($B$5:$B$88,A93,D$5:D$88) -> 0.82009317 | D93: =AVERAGEIF($B$5:$B$88,A93,E$5:E$88) -> 0.84614578 | E93: =AVERAGEIF($B$5:$B$88,A93,F$5:F$88) -> 0.95203015 | F93: =AVERAGEIF($B$5:$B$88,A93,G$5:G$88) -> 0.66058489 | G93: =Assumptions!$B$7 -> 0.85
A94: 2 | B94: Baseline | C94: =AVERAGEIF($B$5:$B$88,A94,D$5:D$88) -> 0.83335404 | D94: =AVERAGEIF($B$5:$B$88,A94,E$5:E$88) -> 0.86390675 | E94: =AVERAGEIF($B$5:$B$88,A94,F$5:F$88) -> 0.95334934 | F94: =AVERAGEIF($B$5:$B$88,A94,G$5:G$88) -> 0.68624224 | G94: =Assumptions!$B$7 -> 0.85
A95: 3 | B95: Baseline | C95: =AVERAGEIF($B$5:$B$88,A95,D$5:D$88) -> 0.84019669 | D95: =AVERAGEIF($B$5:$B$88,A95,E$5:E$88) -> 0.87306607 | E95: =AVERAGEIF($B$5:$B$88,A95,F$5:F$88) -> 0.95951756 | F95: =AVERAGEIF($B$5:$B$88,A95,G$5:G$88) -> 0.70380538 | G95: =Assumptions!$B$7 -> 0.85
A96: 4 | B96: Baseline | C96: =AVERAGEIF($B$5:$B$88,A96,D$5:D$88) -> 0.84966874 | D96: =AVERAGEIF($B$5:$B$88,A96,E$5:E$88) -> 0.89280932 | E96: =AVERAGEIF($B$5:$B$88,A96,F$5:F$88) -> 0.95931098 | F96: =AVERAGEIF($B$5:$B$88,A96,G$5:G$88) -> 0.72789855 | G96: =Assumptions!$B$7 -> 0.85
A97: 5 | B97: Implementation | C97: =AVERAGEIF($B$5:$B$88,A97,D$5:D$88) -> 0.85804348 | D97: =AVERAGEIF($B$5:$B$88,A97,E$5:E$88) -> 0.88630141 | E97: =AVERAGEIF($B$5:$B$88,A97,F$5:F$88) -> 0.95948502 | F97: =AVERAGEIF($B$5:$B$88,A97,G$5:G$88) -> 0.72973085 | G97: =Assumptions!$B$7 -> 0.85
A98: 6 | B98: Implementation | C98: =AVERAGEIF($B$5:$B$88,A98,D$5:D$88) -> 0.8644824 | D98: =AVERAGEIF($B$5:$B$88,A98,E$5:E$88) -> 0.89564656 | E98: =AVERAGEIF($B$5:$B$88,A98,F$5:F$88) -> 0.9618589 | F98: =AVERAGEIF($B$5:$B$88,A98,G$5:G$88) -> 0.74473602 | G98: =Assumptions!$B$7 -> 0.85
A99: 7 | B99: Implementation | C99: =AVERAGEIF($B$5:$B$88,A99,D$5:D$88) -> 0.87503106 | D99: =AVERAGEIF($B$5:$B$88,A99,E$5:E$88) -> 0.89618985 | E99: =AVERAGEIF($B$5:$B$88,A99,F$5:F$88) -> 0.96509823 | F99: =AVERAGEIF($B$5:$B$88,A99,G$5:G$88) -> 0.7568499 | G99: =Assumptions!$B$7 -> 0.85
A100: 8 | B100: Implementation | C100: =AVERAGEIF($B$5:$B$88,A100,D$5:D$88) -> 0.89068323 | D100: =AVERAGEIF($B$5:$B$88,A100,E$5:E$88) -> 0.91620796 | E100: =AVERAGEIF($B$5:$B$88,A100,F$5:F$88) -> 0.97039718 | F100: =AVERAGEIF($B$5:$B$88,A100,G$5:G$88) -> 0.79180538 | G100: =Assumptions!$B$7 -> 0.85
A101: 9 | B101: Improved | C101: =AVERAGEIF($B$5:$B$88,A101,D$5:D$88) -> 0.89644928 | D101: =AVERAGEIF($B$5:$B$88,A101,E$5:E$88) -> 0.92583704 | E101: =AVERAGEIF($B$5:$B$88,A101,F$5:F$88) -> 0.96926081 | F101: =AVERAGEIF($B$5:$B$88,A101,G$5:G$88) -> 0.80456832 | G101: =Assumptions!$B$7 -> 0.85
A102: 10 | B102: Improved | C102: =AVERAGEIF($B$5:$B$88,A102,D$5:D$88) -> 0.90942029 | D102: =AVERAGEIF($B$5:$B$88,A102,E$5:E$88) -> 0.92989819 | E102: =AVERAGEIF($B$5:$B$88,A102,F$5:F$88) -> 0.97510378 | F102: =AVERAGEIF($B$5:$B$88,A102,G$5:G$88) -> 0.82458799 | G102: =Assumptions!$B$7 -> 0.85
A103: 11 | B103: Improved | C103: =AVERAGEIF($B$5:$B$88,A103,D$5:D$88) -> 0.91408903 | D103: =AVERAGEIF($B$5:$B$88,A103,E$5:E$88) -> 0.94210617 | E103: =AVERAGEIF($B$5:$B$88,A103,F$5:F$88) -> 0.97751755 | F103: =AVERAGEIF($B$5:$B$88,A103,G$5:G$88) -> 0.84178882 | G103: =Assumptions!$B$7 -> 0.85
A104: 12 | B104: Improved | C104: =AVERAGEIF($B$5:$B$88,A104,D$5:D$88) -> 0.92817805 | D104: =AVERAGEIF($B$5:$B$88,A104,E$5:E$88) -> 0.95511638 | E104: =AVERAGEIF($B$5:$B$88,A104,F$5:F$88) -> 0.97835485 | F104: =AVERAGEIF($B$5:$B$88,A104,G$5:G$88) -> 0.8672971 | G104: =Assumptions!$B$7 -> 0.85
A107: Phase Summary
A108: Phase | B108: Avg Availability | C108: Avg Performance | D108: Avg Quality | E108: Avg OEE
A109: Baseline | B109: =AVERAGEIF($C$5:$C$88,A109,D$5:D$88) -> 0.83582816 | C109: =AVERAGEIF($C$5:$C$88,A109,E$5:E$88) -> 0.86898198 | D109: =AVERAGEIF($C$5:$C$88,A109,F$5:F$88) -> 0.95605201 | E109: =AVERAGEIF($C$5:$C$88,A109,G$5:G$88) -> 0.69463276
A110: Implementation | B110: =AVERAGEIF($C$5:$C$88,A110,D$5:D$88) -> 0.87206004 | C110: =AVERAGEIF($C$5:$C$88,A110,E$5:E$88) -> 0.89858645 | D110: =AVERAGEIF($C$5:$C$88,A110,F$5:F$88) -> 0.96420983 | E110: =AVERAGEIF($C$5:$C$88,A110,G$5:G$88) -> 0.75578054
A111: Improved | B111: =AVERAGEIF($C$5:$C$88,A111,D$5:D$88) -> 0.91203416 | C111: =AVERAGEIF($C$5:$C$88,A111,E$5:E$88) -> 0.93823945 | D111: =AVERAGEIF($C$5:$C$88,A111,F$5:F$88) -> 0.97505925 | E111: =AVERAGEIF($C$5:$C$88,A111,G$5:G$88) -> 0.83456056

Sheet Six_Big_Losses
A1: Six Big Losses — Pareto Analysis
A2: Total equivalent-minutes lost by category over the 12-week study (used to prioritize TPM action)
A4: Loss Category | B4: OEE Bucket | C4: Total Loss (min) | D4: % of Total | E4: Cumulative %
A5: Reduced Speed (Speed Loss) | B5: Performance | C5: =SUM(OEE_Calc!H5:H88) -> 9809.66 | D5: =C5/$C$10 -> 0.35505442 | E5: =D5 -> 0.35505442
A6: Equipment Breakdowns | B6: Availability | C6: =SUM(Raw_Data!E5:E88) -> 6633.8 | D6: =C6/$C$10 -> 0.24010618 | E6: =E5+D6 -> 0.5951606
A7: Changeover / Setup | B7: Availability | C7: =SUM(Raw_Data!F5:F88) -> 4686.7 | D7: =C7/$C$10 -> 0.16963213 | E7: =E6+D7 -> 0.76479273
A8: Minor Stops / Idling | B8: Availability | C8: =SUM(Raw_Data!G5:G88) -> 3365.7 | D8: =C8/$C$10 -> 0.12181937 | E8: =E7+D8 -> 0.8866121
A9: Quality Defects / Rework | B9: Quality | C9: =SUM(OEE_Calc!I5:I88) -> 3132.75 | D9: =C9/$C$10 -> 0.1133879 | E9: =E8+D9 -> 1
A10: Total | C10: =SUM(C5:C9) -> 27628.61

Sheet TPM_Actions
A1: TPM Pillar Action Tracker
A2: Root-cause countermeasures deployed by TPM pillar, mapped to OEE impact
A4: TPM Pillar | B4: Loss / Problem Identified | C4: Root Cause (5-Why) | D4: Countermeasure (Kaizen) | E4: Owner | F4: Target Date | G4: Status | H4: OEE Impact
A5: Autonomous Maintenance | B5: Frequent minor stops on infeed conveyor | C5: Operators not trained to detect early wear; no cleaning/inspection standard | D5: Implemented CIL (Clean-Inspect-Lubricate) checklist + operator ownership of infeed zone | E5: Line Operators / Shift Lead | F5: Week 5 | G5: Complete | H5: +3.0 pp Availability
A6: Planned Maintenance | B6: Recurring gearbox breakdowns on wrapper | C6: Time-based PM interval too long vs. actual duty cycle; no vibration monitoring | D6: Shifted to condition-based maintenance; added vibration sensors + shortened PM interval | E6: Maintenance Engineer | F6: Week 6 | G6: Complete | H6: +4.5 pp Availability
A7: Focused Improvement (Kaizen) | B7: Long product changeovers (avg 75 min) | C7: Internal steps done while line stopped; tools not staged in advance | D7: SMED workshop: converted internal to external setup, pre-staged tool kits, one-touch clamps | E7: Industrial Engineer | F7: Week 6 | G7: Complete | H7: -40 min/changeover
A8: Quality Maintenance | B8: Reject rate elevated at wrapper seal station | C8: Seal temperature drift not detected until downstream inspection | D8: Added inline seal-integrity sensor with real-time alarm; SPC control chart on seal temp | E8: Quality Engineer | F8: Week 7 | G8: Complete | H8: -2.5 pp Reject Rate
A9: Planned Maintenance | B9: Bearing failures causing unplanned stops | C9: No lubrication schedule tied to run-hours; generic OEM interval used | D9: Built run-hour-based lubrication schedule with tagged lube points and checklist | E9: Maintenance Planner | F9: Week 7 | G9: Complete | H9: +1.8 pp Availability
A10: Education & Training | B10: Inconsistent changeover execution across shifts | C10: No standard work / visual aid; tribal knowledge only with senior operators | D10: Created One-Point Lessons (OPLs) and changeover SOP with visual step cards | E10: Training Coordinator | F10: Week 8 | G10: Complete | H10: Reduced changeover variability
A11: Focused Improvement (Kaizen) | B11: Speed losses from micro-jams on flow wrapper | C11: Film tension inconsistent; guide rails mis-aligned after changeover | D11: Standardized film tension settings; added laser-guided rail alignment fixture | E11: Process Engineer | F11: Week 9 | G11: Complete | H11: +3.0 pp Performance
A12: Early Equipment Management | B12: New SKU changeovers still slow despite SMED | C12: Tooling for new SKUs not designed for quick-change compatibility | D12: Fed learnings back to engineering spec for next tooling purchase (DFM for changeover) | E12: Engineering Lead | F12: Week 10 | G12: In Progress | H12: Future-proofing (no direct pp yet)
A13: Safety, Health & Environment | B13: Autonomous maintenance tasks introduced new pinch-point exposure | C13: CIL tasks required access to guarded zones without a safe isolation step | D13: Added LOTO step to CIL checklist and interlock guarding on infeed access panel | E13: EHS Coordinator | F13: Week 8 | G13: Complete | H13: Zero recordable incidents maintained
A14: Office TPM | B14: Downtime data entered manually with 1-2 day lag | C14: No real-time link between line PLC and OEE tracking sheet | D14: Automated downtime/output data feed from line PLC to OEE tracker (foundation for this dashboard) | E14: Continuous Improvement Lead | F14: Week 9 | G14: Complete | H14: Real-time visibility enabled

Sheet Results_Summary
A1: Results Summary & Financial Impact
A2: Baseline vs. Improved comparison — ready for interview walkthrough
A4: Baseline vs. Improved Performance
A5: Metric | B5: Baseline (Wks 1-4) | C5: Improved (Wks 9-12) | D5: Change (pp / abs)
A6: Availability | B6: =OEE_Calc!B109 -> 0.83582816 | C6: =OEE_Calc!B111 -> 0.91203416 | D6: =C6-B6 -> 0.076206004
A7: Performance | B7: =OEE_Calc!C109 -> 0.86898198 | C7: =OEE_Calc!C111 -> 0.93823945 | D7: =C7-B7 -> 0.069257466
A8: Quality | B8: =OEE_Calc!D109 -> 0.95605201 | C8: =OEE_Calc!D111 -> 0.97505925 | D8: =C8-B8 -> 0.019007243
A9: OEE | B9: =OEE_Calc!E109 -> 0.69463276 | C9: =OEE_Calc!E111 -> 0.83456056 | D9: =C9-B9 -> 0.1399278
A12: Financial & Operational Impact (Annualized)
A13: Impact Driver | B13: Value | C13: Calculation Basis
A14: Downtime Reduced (min/day) | B14: =AVERAGEIF(Raw_Data!C5:C88,"Baseline",Raw_Data!H5:H88)-AVERAGEIF(Raw_Data!C5:C88,"Improved",Raw_Data!H5:H88) -> 105.16429 | C14: Avg total downtime/day, Baseline (Wks1-4) minus Improved (Wks9-12)
A15: Extra Good Output Capacity (packs/day) | B15: =(AVERAGEIF(Raw_Data!C5:C88,"Improved",Raw_Data!J5:J88)-AVERAGEIF(Raw_Data!C5:C88,"Baseline",Raw_Data!J5:J88)) -> 17847.643 | C15: Avg total pieces/day, Improved minus Baseline
A16: Annualized Downtime Cost Avoidance | B16: =B14*Assumptions!$B$8*Assumptions!$B$10 -> 1840375 | C16: Downtime saved/day x Cost per minute x Operating days/year
A17: Annualized Reject/Waste Cost Avoidance | B17: =(AVERAGEIF(Raw_Data!C5:C88,"Baseline",Raw_Data!K5:K88)-AVERAGEIF(Raw_Data!C5:C88,"Improved",Raw_Data!K5:K88))*Assumptions!$B$9*Assumptions!$B$10 -> 76775.625 | C17: Reject units/day reduced x Cost per reject unit x Operating days/year
A18: Total Estimated Annualized Savings | B18: =B16+B17 -> 1917150.6 | C18: Downtime cost avoidance + reject/waste cost avoidance
A21: Interview Talking Points (STAR Format)
A22: Situation | B22: A high-speed packaging line was running below industry benchmark OEE (~68%), driven by frequent breakdowns, long changeovers, and inconsistent quality — constraining throughput and putting service levels and case-fill rate at risk.
A23: Task | B23: Lead a structured OEE improvement initiative using the TPM framework to identify the vital-few losses, deploy root-cause countermeasures, and lift OEE toward the 85% world-class benchmark without capital investment in new equipment.
A24: Action | B24: Built a daily OEE tracking model (Availability/Performance/Quality); ran a Pareto on the Six Big Losses to prioritize breakdowns, changeovers, and minor stops; deployed Autonomous Maintenance (CIL) and Planned/Predictive Maintenance to cut unplanned downtime; ran a SMED kaizen to cut changeover time; added inline quality sensing to reduce rework; and stood up a visual, real-time OEE dashboard to sustain the gains.
A25: Result | B25: OEE improved from ~68% (Baseline) to ~82% (Improved) over 12 weeks — a +14 percentage-point gain — reducing changeovers by ~40 minutes each, cutting reject rate by more than half, and unlocking an estimated six-figure annualized cost avoidance in downtime and waste, directly improving line capacity available to the supply chain plan.
A27: Likely Interview Questions to Prepare
A28: • Walk me through how you calculated OEE and why Availability x Performance x Quality, not a simple average.
A29: • How did you decide which losses to attack first? (Pareto principle — vital few vs. trivial many)
A30: • What would you do differently if the top loss had been Quality instead of Availability?
A31: • How do you sustain the gains after the project team moves on? (visual management, OPLs, layered audits)
A32: • How does line-level OEE improvement translate into supply chain KPIs (case fill rate, OTIF, inventory buffers)?
A33: • If Finance challenged your cost-avoidance number, how would you defend the $/minute downtime assumption?
